rakuten_ws/__init__.py
rakuten_ws/baseapi.py
rakuten_ws/baserms.py
rakuten_ws/parameters.py
rakuten_ws/utils.py
rakuten_ws/webservice.py
rakuten_ws/wsdl/inventoryapi.wsdl
rakuten_ws/wsdl/orderapi.wsdl
rakuten_ws-0.5.2.dist-info/AUTHORS.rst
rakuten_ws-0.5.2.dist-info/LICENSE
rakuten_ws-0.5.2.dist-info/METADATA
rakuten_ws-0.5.2.dist-info/WHEEL
rakuten_ws-0.5.2.dist-info/top_level.txt
rakuten_ws-0.5.2.dist-info/RECORD
