Metadata-Version: 2.1
Name: rakuten-ws
Version: 0.5.2
Summary: Unofficial Python Client for Rakuten Web Service
Home-page: https://github.com/alexandriagroup/rakuten-ws
Author: Damien Rabois
Author-email: damien.rabois@abc-culture.fr
License: MIT license
Keywords: rakuten-ws
Classifier: Development Status :: 2 - Pre-Alpha
Classifier: Intended Audience :: Developers
Classifier: License :: OSI Approved :: MIT License
Classifier: Natural Language :: English
Classifier: Programming Language :: Python :: 3
License-File: LICENSE
License-File: AUTHORS.rst
Requires-Dist: furl
Requires-Dist: requests
Requires-Dist: zeep
Requires-Dist: xmljson
